typeguard/__init__.py
typeguard/_checkers.py
typeguard/_config.py
typeguard/_decorators.py
typeguard/_exceptions.py
typeguard/_functions.py
typeguard/_importhook.py
typeguard/_memo.py
typeguard/_pytest_plugin.py
typeguard/_suppression.py
typeguard/_transformer.py
typeguard/_union_transformer.py
typeguard/_utils.py
typeguard/py.typed
typing_extensions/typing_extensions.py
wypp/__init__.py
wypp/ansi.py
wypp/cmdlineArgs.py
wypp/constants.py
wypp/debug.py
wypp/drawingLib.py
wypp/errors.py
wypp/exceptionHandler.py
wypp/i18n.py
wypp/instrument.py
wypp/interactive.py
wypp/lang.py
wypp/location.py
wypp/myLogging.py
wypp/myTypeguard.py
wypp/parsecache.py
wypp/paths.py
wypp/records.py
wypp/renderTy.py
wypp/replTester.py
wypp/runCode.py
wypp/runYourProgram.py
wypp/runner.py
wypp/stacktrace.py
wypp/typecheck.py
wypp/utils.py
wypp/version.py
wypp/writeYourProgram.py
wypp-2.1.2.data/scripts/wypp
wypp-2.1.2.dist-info/licenses/LICENSE
wypp-2.1.2.dist-info/METADATA
wypp-2.1.2.dist-info/WHEEL
wypp-2.1.2.dist-info/top_level.txt
wypp-2.1.2.dist-info/RECORD
