Metadata-Version: 2.4
Name: wypp
Version: 2.1.2
Summary: A user-friendly python programming environment for beginners
Home-page: https://github.com/skogsbaer/write-your-python-program
Author: Stefan Wehr
Author-email: stefan.wehr@hs-offenburg.de
Requires-Python: >=3.12.0
License-File: LICENSE
Dynamic: author
Dynamic: author-email
Dynamic: description
Dynamic: description-content-type
Dynamic: home-page
Dynamic: license-file
Dynamic: requires-python
Dynamic: summary
